README.md
pyproject.toml
setup.py
img_phy_sim/__init__.py
img_phy_sim/data.py
img_phy_sim/eval.py
img_phy_sim/img.py
img_phy_sim/ism.py
img_phy_sim/ism_slow.py
img_phy_sim/math.py
img_phy_sim/ray_tracing.py
img_phy_sim.egg-info/PKG-INFO
img_phy_sim.egg-info/SOURCES.txt
img_phy_sim.egg-info/dependency_links.txt
img_phy_sim.egg-info/requires.txt
img_phy_sim.egg-info/top_level.txt