Metadata-Version: 2.4
Name: img-phy-sim
Version: 0.9
Summary: Physical Simulations on Images.
Home-page: https://github.com/M-106/Image-Physics-Simulation
Download-URL: https://github.com/M-106/Image-Physics-Simulation/archive/v_04.tar.gz
Author: Tobia Ippolito
Project-URL: Documentation, https://M-106.github.io/Image-Physics-Simulation/img_phy_sim
Project-URL: Source, https://github.com/M-106/Image-Physics-Simulation
Keywords: Simulation,Computer-Vision,Physgen
Classifier: Programming Language :: Python :: 3
Classifier: Operating System :: OS Independent
Classifier: Programming Language :: Python :: 3.8
Classifier: Programming Language :: Python :: 3.9
Classifier: Programming Language :: Python :: 3.10
Classifier: Programming Language :: Python :: 3.11
Classifier: Programming Language :: Python :: 3.12
Classifier: Programming Language :: Python :: 3.13
Requires-Dist: numpy
Requires-Dist: opencv-python
Requires-Dist: matplotlib
Requires-Dist: scikit-image
Requires-Dist: joblib
Requires-Dist: shapely
Provides-Extra: full
Requires-Dist: torch; extra == "full"
Requires-Dist: torchvision; extra == "full"
Requires-Dist: datasets==3.6.0; extra == "full"
Requires-Dist: prime_printer; extra == "full"
Dynamic: author
Dynamic: classifier
Dynamic: description
Dynamic: description-content-type
Dynamic: download-url
Dynamic: home-page
Dynamic: keywords
Dynamic: project-url
Dynamic: provides-extra
Dynamic: requires-dist
Dynamic: summary
